{
    "channel_name": "兵团卫视",
    "date": "2026-01-31",
    "epg_data": [
        {
            "start": "00:34",
            "end": "01:06",
            "title": " 生活服务",
            "desc": ""
        },
        {
            "start": "01:06",
            "end": "01:52",
            "title": " 午夜剧场:山海情10",
            "desc": ""
        },
        {
            "start": "01:52",
            "end": "02:39",
            "title": "第10集剧情演员表",
            "desc": ""
        },
        {
            "start": "02:39",
            "end": "03:25",
            "title": "第11集剧情演员表",
            "desc": ""
        },
        {
            "start": "03:25",
            "end": "04:07",
            "title": "第12集剧情演员表",
            "desc": ""
        },
        {
            "start": "04:07",
            "end": "04:27",
            "title": "第13集剧情演员表",
            "desc": ""
        },
        {
            "start": "04:27",
            "end": "04:38",
            "title": " 我的兵团岁月",
            "desc": ""
        },
        {
            "start": "04:38",
            "end": "05:26",
            "title": " 西行漫纪",
            "desc": ""
        },
        {
            "start": "05:26",
            "end": "06:09",
            "title": "第14集剧情演员表",
            "desc": ""
        },
        {
            "start": "06:09",
            "end": "06:39",
            "title": "第1集剧情演员表",
            "desc": ""
        },
        {
            "start": "06:39",
            "end": "07:22",
            "title": " 生活服务",
            "desc": ""
        },
        {
            "start": "07:22",
            "end": "07:54",
            "title": "第2集剧情演员表",
            "desc": ""
        },
        {
            "start": "07:54",
            "end": "08:30",
            "title": " 生活服务",
            "desc": ""
        },
        {
            "start": "08:30",
            "end": "09:00",
            "title": " 我的兵团岁月",
            "desc": ""
        },
        {
            "start": "09:00",
            "end": "09:08",
            "title": " 兵团新闻联播",
            "desc": ""
        },
        {
            "start": "09:08",
            "end": "09:50",
            "title": " 中华人民共和国国歌",
            "desc": ""
        },
        {
            "start": "09:50",
            "end": "10:17",
            "title": "第14集剧情演员表",
            "desc": ""
        },
        {
            "start": "10:17",
            "end": "10:59",
            "title": " 生活服务",
            "desc": ""
        },
        {
            "start": "10:59",
            "end": "11:27",
            "title": "第15集剧情演员表",
            "desc": ""
        },
        {
            "start": "11:27",
            "end": "12:08",
            "title": " 生活服务",
            "desc": ""
        },
        {
            "start": "12:08",
            "end": "12:45",
            "title": "第16集剧情演员表",
            "desc": ""
        },
        {
            "start": "12:45",
            "end": "13:27",
            "title": " 生活服务",
            "desc": ""
        },
        {
            "start": "13:27",
            "end": "14:00",
            "title": "第17集剧情演员表",
            "desc": ""
        },
        {
            "start": "14:00",
            "end": "14:36",
            "title": " 生活服务",
            "desc": ""
        },
        {
            "start": "14:36",
            "end": "15:18",
            "title": " 直击民生",
            "desc": ""
        },
        {
            "start": "15:18",
            "end": "15:44",
            "title": "第7集剧情演员表",
            "desc": ""
        },
        {
            "start": "15:44",
            "end": "16:26",
            "title": " 生活服务",
            "desc": ""
        },
        {
            "start": "16:26",
            "end": "16:59",
            "title": "第8集剧情演员表",
            "desc": ""
        },
        {
            "start": "16:59",
            "end": "17:42",
            "title": " 生活服务",
            "desc": ""
        },
        {
            "start": "17:42",
            "end": "18:11",
            "title": "第9集剧情演员表",
            "desc": ""
        },
        {
            "start": "18:11",
            "end": "18:27",
            "title": " 生活服务",
            "desc": ""
        },
        {
            "start": "18:27",
            "end": "19:00",
            "title": " 为新时代放歌",
            "desc": ""
        },
        {
            "start": "19:00",
            "end": "19:30",
            "title": " 动画片:银河封神纪",
            "desc": ""
        },
        {
            "start": "19:30",
            "end": "19:32",
            "title": " 转播中央台新闻联播",
            "desc": ""
        },
        {
            "start": "19:32",
            "end": "20:00",
            "title": " 广告",
            "desc": ""
        },
        {
            "start": "20:00",
            "end": "20:25",
            "title": " 西行漫纪",
            "desc": ""
        },
        {
            "start": "20:25",
            "end": "20:30",
            "title": " 兵团新闻联播",
            "desc": ""
        },
        {
            "start": "20:30",
            "end": "20:50",
            "title": " 天气预报",
            "desc": ""
        },
        {
            "start": "20:50",
            "end": "20:55",
            "title": " 兵团视点",
            "desc": ""
        },
        {
            "start": "20:55",
            "end": "21:17",
            "title": " 科普兵团",
            "desc": ""
        },
        {
            "start": "21:17",
            "end": "22:00",
            "title": " 为新时代放歌",
            "desc": ""
        },
        {
            "start": "22:00",
            "end": "22:30",
            "title": "第33集剧情演员表",
            "desc": ""
        },
        {
            "start": "22:30",
            "end": "23:04",
            "title": " 兵团新闻联播",
            "desc": ""
        },
        {
            "start": "23:04",
            "end": "23:15",
            "title": " 叩问初心",
            "desc": ""
        },
        {
            "start": "23:15",
            "end": "23:25",
            "title": " 西行漫纪",
            "desc": ""
        },
        {
            "start": "23:25",
            "end": "23:43",
            "title": " 兵团榜样",
            "desc": ""
        },
        {
            "start": "23:43",
            "end": "00:00",
            "title": " 纪录片:马王堆岁月不朽8",
            "desc": ""
        }
    ]
}