{
    "channel_name": "嘉佳卡通",
    "date": "2024-05-23",
    "epg_data": [
        {
            "start": "00:03",
            "end": "00:14",
            "title": "猪猪侠之竞速小英雄Ⅶ1",
            "desc": ""
        },
        {
            "start": "00:14",
            "end": "00:25",
            "title": "猪猪侠之竞速小英雄Ⅶ2",
            "desc": ""
        },
        {
            "start": "00:25",
            "end": "00:36",
            "title": "猪猪侠之竞速小英雄Ⅶ3",
            "desc": ""
        },
        {
            "start": "00:36",
            "end": "00:47",
            "title": "猪猪侠之竞速小英雄Ⅶ4",
            "desc": ""
        },
        {
            "start": "00:47",
            "end": "00:58",
            "title": "猪猪侠之竞速小英雄Ⅶ5",
            "desc": ""
        },
        {
            "start": "00:58",
            "end": "01:09",
            "title": "猪猪侠之竞速小英雄Ⅶ6",
            "desc": ""
        },
        {
            "start": "01:09",
            "end": "01:20",
            "title": "猪猪侠之竞速小英雄Ⅶ7",
            "desc": ""
        },
        {
            "start": "01:20",
            "end": "01:31",
            "title": "猪猪侠之竞速小英雄Ⅶ8",
            "desc": ""
        },
        {
            "start": "01:31",
            "end": "01:42",
            "title": "猪猪侠之竞速小英雄Ⅶ9",
            "desc": ""
        },
        {
            "start": "01:42",
            "end": "01:53",
            "title": "猪猪侠之竞速小英雄Ⅶ10",
            "desc": ""
        },
        {
            "start": "01:53",
            "end": "02:04",
            "title": "猪猪侠之竞速小英雄Ⅶ11",
            "desc": ""
        },
        {
            "start": "02:04",
            "end": "02:15",
            "title": "猪猪侠之竞速小英雄Ⅶ12",
            "desc": ""
        },
        {
            "start": "02:15",
            "end": "02:26",
            "title": "猪猪侠之竞速小英雄Ⅶ13",
            "desc": ""
        },
        {
            "start": "02:26",
            "end": "02:37",
            "title": "猪猪侠之竞速小英雄Ⅶ14",
            "desc": ""
        },
        {
            "start": "02:37",
            "end": "02:48",
            "title": "猪猪侠之竞速小英雄Ⅶ15",
            "desc": ""
        },
        {
            "start": "02:48",
            "end": "02:59",
            "title": "猪猪侠之竞速小英雄Ⅶ16",
            "desc": ""
        },
        {
            "start": "02:59",
            "end": "03:10",
            "title": "猪猪侠之竞速小英雄Ⅶ17",
            "desc": ""
        },
        {
            "start": "03:10",
            "end": "03:21",
            "title": "猪猪侠之竞速小英雄Ⅶ18",
            "desc": ""
        },
        {
            "start": "03:21",
            "end": "03:32",
            "title": "猪猪侠之竞速小英雄Ⅶ19",
            "desc": ""
        },
        {
            "start": "03:32",
            "end": "03:43",
            "title": "猪猪侠之竞速小英雄Ⅶ20",
            "desc": ""
        },
        {
            "start": "03:43",
            "end": "03:54",
            "title": "猪猪侠之竞速小英雄Ⅶ21",
            "desc": ""
        },
        {
            "start": "03:54",
            "end": "04:05",
            "title": "猪猪侠之竞速小英雄Ⅶ22",
            "desc": ""
        },
        {
            "start": "04:05",
            "end": "04:16",
            "title": "猪猪侠之竞速小英雄Ⅶ23",
            "desc": ""
        },
        {
            "start": "04:16",
            "end": "04:27",
            "title": "猪猪侠之竞速小英雄Ⅶ24",
            "desc": ""
        },
        {
            "start": "04:27",
            "end": "04:38",
            "title": "猪猪侠之竞速小英雄Ⅶ25",
            "desc": ""
        },
        {
            "start": "04:38",
            "end": "04:49",
            "title": "猪猪侠之竞速小英雄Ⅶ26",
            "desc": ""
        },
        {
            "start": "04:49",
            "end": "05:00",
            "title": "猪猪侠之竞速小英雄Ⅶ1",
            "desc": ""
        },
        {
            "start": "05:00",
            "end": "05:11",
            "title": "猪猪侠之竞速小英雄Ⅶ2",
            "desc": ""
        },
        {
            "start": "05:11",
            "end": "05:22",
            "title": "猪猪侠之竞速小英雄Ⅶ3",
            "desc": ""
        },
        {
            "start": "05:22",
            "end": "05:33",
            "title": "猪猪侠之竞速小英雄Ⅶ4",
            "desc": ""
        },
        {
            "start": "05:33",
            "end": "05:44",
            "title": "猪猪侠之竞速小英雄Ⅶ5",
            "desc": ""
        },
        {
            "start": "05:44",
            "end": "05:59",
            "title": "猪猪侠之竞速小英雄Ⅶ6",
            "desc": ""
        },
        {
            "start": "05:59",
            "end": "06:12",
            "title": "猪猪侠之竞速小英雄Ⅵ21",
            "desc": ""
        },
        {
            "start": "06:12",
            "end": "06:25",
            "title": "猪猪侠之竞速小英雄Ⅵ22",
            "desc": ""
        },
        {
            "start": "06:25",
            "end": "06:36",
            "title": "猪猪侠之竞速小英雄Ⅵ23",
            "desc": ""
        },
        {
            "start": "06:36",
            "end": "06:47",
            "title": "猪猪侠之竞速小英雄Ⅵ24",
            "desc": ""
        },
        {
            "start": "06:47",
            "end": "06:58",
            "title": "猪猪侠之竞速小英雄Ⅵ25",
            "desc": ""
        },
        {
            "start": "06:58",
            "end": "07:11",
            "title": "猪猪侠之竞速小英雄Ⅵ26",
            "desc": ""
        },
        {
            "start": "07:11",
            "end": "07:23",
            "title": "猪猪侠之竞速小英雄Ⅴ1",
            "desc": ""
        },
        {
            "start": "07:23",
            "end": "07:36",
            "title": "猪猪侠之竞速小英雄Ⅴ2",
            "desc": ""
        },
        {
            "start": "07:36",
            "end": "07:49",
            "title": "猪猪侠之竞速小英雄Ⅴ3",
            "desc": ""
        },
        {
            "start": "07:49",
            "end": "08:00",
            "title": "猪猪侠之竞速小英雄Ⅴ4",
            "desc": ""
        },
        {
            "start": "08:00",
            "end": "08:14",
            "title": "猪猪侠之竞速小英雄Ⅴ5",
            "desc": ""
        },
        {
            "start": "08:14",
            "end": "08:25",
            "title": "猪猪侠之竞速小英雄Ⅴ6",
            "desc": ""
        },
        {
            "start": "08:25",
            "end": "08:38",
            "title": "猪猪侠之竞速小英雄Ⅴ7",
            "desc": ""
        },
        {
            "start": "08:38",
            "end": "08:49",
            "title": "超级飞侠ⅩⅥ10",
            "desc": ""
        },
        {
            "start": "08:49",
            "end": "09:12",
            "title": "超级飞侠ⅩⅥ11",
            "desc": ""
        },
        {
            "start": "09:12",
            "end": "09:23",
            "title": "超级飞侠ⅩⅥ12",
            "desc": ""
        },
        {
            "start": "09:23",
            "end": "09:34",
            "title": "超级飞侠ⅩⅥ13",
            "desc": ""
        },
        {
            "start": "09:34",
            "end": "09:45",
            "title": "超级飞侠ⅩⅥ14",
            "desc": ""
        },
        {
            "start": "09:45",
            "end": "09:56",
            "title": "超级飞侠ⅩⅥ15",
            "desc": ""
        },
        {
            "start": "09:56",
            "end": "10:18",
            "title": "超级飞侠ⅩⅥ16",
            "desc": ""
        },
        {
            "start": "10:18",
            "end": "10:29",
            "title": "超级飞侠ⅩⅥ17",
            "desc": ""
        },
        {
            "start": "10:29",
            "end": "10:40",
            "title": "超级飞侠ⅩⅥ18",
            "desc": ""
        },
        {
            "start": "10:40",
            "end": "10:51",
            "title": "超级飞侠ⅩⅥ19",
            "desc": ""
        },
        {
            "start": "10:51",
            "end": "11:02",
            "title": "超级飞侠ⅩⅥ20",
            "desc": ""
        },
        {
            "start": "11:02",
            "end": "11:14",
            "title": "故事光",
            "desc": ""
        },
        {
            "start": "11:14",
            "end": "11:25",
            "title": "熊出没之怪兽计划Ⅱ31",
            "desc": ""
        },
        {
            "start": "11:25",
            "end": "11:36",
            "title": "熊出没之怪兽计划Ⅱ32",
            "desc": ""
        },
        {
            "start": "11:36",
            "end": "11:47",
            "title": "熊出没之怪兽计划Ⅱ33",
            "desc": ""
        },
        {
            "start": "11:47",
            "end": "11:58",
            "title": "熊出没之怪兽计划Ⅱ34",
            "desc": ""
        },
        {
            "start": "11:58",
            "end": "12:11",
            "title": "熊出没之怪兽计划Ⅱ35",
            "desc": ""
        },
        {
            "start": "12:11",
            "end": "12:24",
            "title": "熊出没之怪兽计划Ⅱ36",
            "desc": ""
        },
        {
            "start": "12:24",
            "end": "12:37",
            "title": "熊出没之怪兽计划Ⅱ37",
            "desc": ""
        },
        {
            "start": "12:37",
            "end": "12:48",
            "title": "熊出没之怪兽计划Ⅱ38",
            "desc": ""
        },
        {
            "start": "12:48",
            "end": "12:59",
            "title": "熊出没之怪兽计划Ⅱ39",
            "desc": ""
        },
        {
            "start": "12:59",
            "end": "13:12",
            "title": "熊出没之怪兽计划Ⅱ40",
            "desc": ""
        },
        {
            "start": "13:12",
            "end": "13:24",
            "title": "熊出没之怪兽计划Ⅱ41",
            "desc": ""
        },
        {
            "start": "13:24",
            "end": "13:36",
            "title": "熊出没之怪兽计划Ⅱ42",
            "desc": ""
        },
        {
            "start": "13:36",
            "end": "13:47",
            "title": "超级飞侠ⅩⅥ15",
            "desc": ""
        },
        {
            "start": "13:47",
            "end": "13:58",
            "title": "超级飞侠ⅩⅥ16",
            "desc": ""
        },
        {
            "start": "13:58",
            "end": "14:12",
            "title": "故事光",
            "desc": ""
        },
        {
            "start": "14:12",
            "end": "14:23",
            "title": "熊出没之怪兽计划Ⅱ1",
            "desc": ""
        },
        {
            "start": "14:23",
            "end": "14:34",
            "title": "熊出没之怪兽计划Ⅱ2",
            "desc": ""
        },
        {
            "start": "14:34",
            "end": "14:45",
            "title": "熊出没之怪兽计划Ⅱ3",
            "desc": ""
        },
        {
            "start": "14:45",
            "end": "14:56",
            "title": "熊出没之怪兽计划Ⅱ4",
            "desc": ""
        },
        {
            "start": "14:56",
            "end": "15:10",
            "title": "熊出没之怪兽计划Ⅱ5",
            "desc": ""
        },
        {
            "start": "15:10",
            "end": "15:23",
            "title": "熊出没之怪兽计划Ⅱ6",
            "desc": ""
        },
        {
            "start": "15:23",
            "end": "15:38",
            "title": "熊出没之怪兽计划Ⅱ7",
            "desc": ""
        },
        {
            "start": "15:38",
            "end": "15:49",
            "title": "熊出没之怪兽计划Ⅱ8",
            "desc": ""
        },
        {
            "start": "15:49",
            "end": "16:10",
            "title": "熊出没之怪兽计划Ⅱ9",
            "desc": ""
        },
        {
            "start": "16:10",
            "end": "16:21",
            "title": "超级飞侠Ⅺ6",
            "desc": ""
        },
        {
            "start": "16:21",
            "end": "16:32",
            "title": "超级飞侠Ⅺ7",
            "desc": ""
        },
        {
            "start": "16:32",
            "end": "16:43",
            "title": "超级飞侠Ⅺ8",
            "desc": ""
        },
        {
            "start": "16:43",
            "end": "16:54",
            "title": "超级飞侠Ⅺ9",
            "desc": ""
        },
        {
            "start": "16:54",
            "end": "17:07",
            "title": "2023朗朗盛典展播(30)",
            "desc": ""
        },
        {
            "start": "17:07",
            "end": "17:29",
            "title": "卡卡虎大冒险Ⅲ8",
            "desc": ""
        },
        {
            "start": "17:29",
            "end": "17:42",
            "title": "吼吼龙守卫队11",
            "desc": ""
        },
        {
            "start": "17:42",
            "end": "17:54",
            "title": "超级飞侠Ⅺ10",
            "desc": ""
        },
        {
            "start": "17:54",
            "end": "18:07",
            "title": "超级飞侠Ⅺ11",
            "desc": ""
        },
        {
            "start": "18:07",
            "end": "18:18",
            "title": "超级飞侠Ⅺ12",
            "desc": ""
        },
        {
            "start": "18:18",
            "end": "18:31",
            "title": "超级飞侠Ⅺ13",
            "desc": ""
        },
        {
            "start": "18:31",
            "end": "18:44",
            "title": "超级飞侠ⅩⅥ15",
            "desc": ""
        },
        {
            "start": "18:44",
            "end": "18:58",
            "title": "超级飞侠ⅩⅥ16",
            "desc": ""
        },
        {
            "start": "18:58",
            "end": "19:10",
            "title": "巴啦啦小魔仙之星缘蝶启Ⅱ(23)",
            "desc": ""
        },
        {
            "start": "19:10",
            "end": "19:23",
            "title": "变形联盟-时空危机3",
            "desc": ""
        },
        {
            "start": "19:23",
            "end": "19:34",
            "title": "猪猪侠之超星五灵侠Ⅳ(16)",
            "desc": ""
        },
        {
            "start": "19:34",
            "end": "19:47",
            "title": "猪猪侠之超星五灵侠Ⅳ(17)",
            "desc": ""
        },
        {
            "start": "19:47",
            "end": "19:59",
            "title": "猪猪侠之超星五灵侠Ⅳ(18)",
            "desc": ""
        },
        {
            "start": "19:59",
            "end": "20:05",
            "title": "大玩家:量子开箱(16)",
            "desc": ""
        },
        {
            "start": "20:05",
            "end": "20:10",
            "title": "大玩家:小特搜员(44)",
            "desc": ""
        },
        {
            "start": "20:10",
            "end": "20:23",
            "title": "猪猪侠之超星五灵侠Ⅳ(19)",
            "desc": ""
        },
        {
            "start": "20:23",
            "end": "20:36",
            "title": "猪猪侠之超星五灵侠Ⅳ(20)",
            "desc": ""
        },
        {
            "start": "20:36",
            "end": "20:49",
            "title": "猪猪侠之超星五灵侠Ⅳ(21)",
            "desc": ""
        },
        {
            "start": "20:49",
            "end": "21:00",
            "title": "猪猪侠之超星五灵侠Ⅳ(22)",
            "desc": ""
        },
        {
            "start": "21:00",
            "end": "21:07",
            "title": "嗨!小喇叭:百园计划(9)-富康等",
            "desc": ""
        },
        {
            "start": "21:07",
            "end": "21:18",
            "title": "猪猪侠之超星五灵侠Ⅳ(23)",
            "desc": ""
        },
        {
            "start": "21:18",
            "end": "21:31",
            "title": "猪猪侠之超星五灵侠Ⅳ(24)",
            "desc": ""
        },
        {
            "start": "21:31",
            "end": "21:45",
            "title": "猪猪侠之超星五灵侠Ⅳ(25)",
            "desc": ""
        },
        {
            "start": "21:45",
            "end": "21:58",
            "title": "猪猪侠之超星五灵侠Ⅳ(26)",
            "desc": ""
        },
        {
            "start": "21:58",
            "end": "22:12",
            "title": "猪猪侠之超星五灵侠Ⅴ1",
            "desc": ""
        },
        {
            "start": "22:12",
            "end": "22:26",
            "title": "猪猪侠之超星五灵侠Ⅴ2",
            "desc": ""
        },
        {
            "start": "22:26",
            "end": "22:39",
            "title": "猪猪侠之超星五灵侠Ⅴ3",
            "desc": ""
        },
        {
            "start": "22:39",
            "end": "22:51",
            "title": "猪猪侠之超星五灵侠Ⅴ4",
            "desc": ""
        },
        {
            "start": "22:51",
            "end": "23:02",
            "title": "猪猪侠之超星五灵侠Ⅴ5",
            "desc": ""
        },
        {
            "start": "23:02",
            "end": "23:15",
            "title": "猪猪侠之超星五灵侠Ⅴ6",
            "desc": ""
        },
        {
            "start": "23:15",
            "end": "23:26",
            "title": "猪猪侠之超星五灵侠Ⅴ7",
            "desc": ""
        },
        {
            "start": "23:26",
            "end": "23:39",
            "title": "猪猪侠之超星五灵侠Ⅴ8",
            "desc": ""
        },
        {
            "start": "23:39",
            "end": "23:52",
            "title": "猪猪侠之超星五灵侠Ⅴ9",
            "desc": ""
        },
        {
            "start": "23:52",
            "end": "00:00",
            "title": "猪猪侠之超星五灵侠Ⅴ10",
            "desc": ""
        }
    ]
}