{
    "channel_name": "CCTV17农业农村",
    "date": "2026-04-29",
    "epg_data": [
        {
            "start": "00:14",
            "end": "05:56",
            "title": "超级农人秀-2026-84",
            "desc": ""
        },
        {
            "start": "05:56",
            "end": "06:05",
            "title": "2026田园特供-乡村达人秀11-川剧三绝表演",
            "desc": ""
        },
        {
            "start": "06:05",
            "end": "06:30",
            "title": "田园帮帮团-2026-68",
            "desc": ""
        },
        {
            "start": "06:30",
            "end": "06:57",
            "title": "超级农人秀-2026-84",
            "desc": ""
        },
        {
            "start": "06:57",
            "end": "07:23",
            "title": "共富经-2025-110",
            "desc": ""
        },
        {
            "start": "07:23",
            "end": "07:50",
            "title": "谁知盘中餐-2026-80",
            "desc": ""
        },
        {
            "start": "07:50",
            "end": "08:20",
            "title": "中国三农报道",
            "desc": ""
        },
        {
            "start": "08:20",
            "end": "08:51",
            "title": "三农群英汇-2026-157",
            "desc": ""
        },
        {
            "start": "08:51",
            "end": "09:21",
            "title": "田园帮帮团-2026-68",
            "desc": ""
        },
        {
            "start": "09:21",
            "end": "09:48",
            "title": "超级农人秀-2026-84",
            "desc": ""
        },
        {
            "start": "09:48",
            "end": "10:17",
            "title": "共富经-2025-110",
            "desc": ""
        },
        {
            "start": "10:17",
            "end": "11:10",
            "title": "我和我的三个姐姐17/38",
            "desc": ""
        },
        {
            "start": "11:10",
            "end": "12:00",
            "title": "我和我的三个姐姐18/38",
            "desc": ""
        },
        {
            "start": "12:00",
            "end": "13:01",
            "title": "中国三农报道",
            "desc": ""
        },
        {
            "start": "13:01",
            "end": "13:28",
            "title": "田园帮帮团-2026-68",
            "desc": ""
        },
        {
            "start": "13:28",
            "end": "13:38",
            "title": "2026田园特供-乡村达人秀16-蹬技表演",
            "desc": ""
        },
        {
            "start": "13:38",
            "end": "14:29",
            "title": "破冰行动2/43",
            "desc": ""
        },
        {
            "start": "14:29",
            "end": "15:20",
            "title": "破冰行动3/43",
            "desc": ""
        },
        {
            "start": "15:20",
            "end": "16:13",
            "title": "破冰行动4/43",
            "desc": ""
        },
        {
            "start": "16:13",
            "end": "17:04",
            "title": "破冰行动5/43",
            "desc": ""
        },
        {
            "start": "17:04",
            "end": "17:32",
            "title": "乡土中国-2025-9",
            "desc": ""
        },
        {
            "start": "17:32",
            "end": "18:00",
            "title": "谁知盘中餐-2026-81",
            "desc": ""
        },
        {
            "start": "18:00",
            "end": "18:39",
            "title": "中国三农报道",
            "desc": ""
        },
        {
            "start": "18:39",
            "end": "19:34",
            "title": "我和我的三个姐姐19/38",
            "desc": ""
        },
        {
            "start": "19:34",
            "end": "20:30",
            "title": "我和我的三个姐姐20/38",
            "desc": ""
        },
        {
            "start": "20:30",
            "end": "21:00",
            "title": "三农群英汇-2026-158",
            "desc": ""
        },
        {
            "start": "21:00",
            "end": "21:30",
            "title": "共富经-2026-72",
            "desc": ""
        },
        {
            "start": "21:30",
            "end": "21:58",
            "title": "超级农人秀-2026-85",
            "desc": ""
        },
        {
            "start": "21:58",
            "end": "22:25",
            "title": "田园帮帮团-2026-9",
            "desc": ""
        },
        {
            "start": "22:25",
            "end": "22:52",
            "title": "谁知盘中餐-2026-81",
            "desc": ""
        },
        {
            "start": "22:52",
            "end": "23:21",
            "title": "三农群英汇-2026-158",
            "desc": ""
        },
        {
            "start": "23:21",
            "end": "23:47",
            "title": "共富经-2026-72",
            "desc": ""
        },
        {
            "start": "23:47",
            "end": "23:59",
            "title": "乡土中国-2025-9",
            "desc": ""
        }
    ]
}