{
    "channel_name": "CCTV7国防军事",
    "date": "2026-07-02",
    "epg_data": [
        {
            "start": "00:29",
            "end": "01:21",
            "title": "五星剧场-我们的河山16/36",
            "desc": ""
        },
        {
            "start": "01:21",
            "end": "01:55",
            "title": "军事纪实-2026-130",
            "desc": ""
        },
        {
            "start": "01:55",
            "end": "02:42",
            "title": "兵器面面观-2026-130",
            "desc": ""
        },
        {
            "start": "02:42",
            "end": "06:03",
            "title": "再见",
            "desc": ""
        },
        {
            "start": "06:03",
            "end": "06:33",
            "title": "军事纪实-2026-130",
            "desc": ""
        },
        {
            "start": "06:33",
            "end": "06:59",
            "title": "国防故事-2026-86",
            "desc": ""
        },
        {
            "start": "06:59",
            "end": "07:24",
            "title": "世界战史-2026-125",
            "desc": ""
        },
        {
            "start": "07:24",
            "end": "07:30",
            "title": "国防微视频-军歌嘹亮-人民陆军进行曲（2026）",
            "desc": ""
        },
        {
            "start": "07:30",
            "end": "08:08",
            "title": "国防军事早报",
            "desc": ""
        },
        {
            "start": "08:08",
            "end": "09:11",
            "title": "讲武堂-2026-26",
            "desc": ""
        },
        {
            "start": "09:11",
            "end": "09:43",
            "title": "防务新观察-2026-182",
            "desc": ""
        },
        {
            "start": "09:43",
            "end": "10:13",
            "title": "军事纪实-2026-130",
            "desc": ""
        },
        {
            "start": "10:13",
            "end": "10:41",
            "title": "兵器面面观-2026-130",
            "desc": ""
        },
        {
            "start": "10:41",
            "end": "11:03",
            "title": "世界战史-2026-125",
            "desc": ""
        },
        {
            "start": "11:03",
            "end": "11:30",
            "title": "国防故事-2026-86",
            "desc": ""
        },
        {
            "start": "11:30",
            "end": "12:00",
            "title": "军事纪录-2026-125",
            "desc": ""
        },
        {
            "start": "12:00",
            "end": "12:36",
            "title": "正午国防军事",
            "desc": ""
        },
        {
            "start": "12:36",
            "end": "13:10",
            "title": "防务新观察-2026-182",
            "desc": ""
        },
        {
            "start": "13:10",
            "end": "13:39",
            "title": "军营的味道-2026-26",
            "desc": ""
        },
        {
            "start": "13:39",
            "end": "14:06",
            "title": "兵器面面观-2026-130",
            "desc": ""
        },
        {
            "start": "14:06",
            "end": "14:34",
            "title": "军事纪录-2026-125",
            "desc": ""
        },
        {
            "start": "14:34",
            "end": "15:24",
            "title": "浴血十四年39/40",
            "desc": ""
        },
        {
            "start": "15:24",
            "end": "16:13",
            "title": "浴血十四年40/40",
            "desc": ""
        },
        {
            "start": "16:13",
            "end": "17:04",
            "title": "黑白禁区1/42",
            "desc": ""
        },
        {
            "start": "17:04",
            "end": "17:31",
            "title": "世界战史-2026-126",
            "desc": ""
        },
        {
            "start": "17:31",
            "end": "18:00",
            "title": "军事纪录-2026-126",
            "desc": ""
        },
        {
            "start": "18:00",
            "end": "18:02",
            "title": "国防微视频-军歌嘹亮-人民陆军进行曲（2026）",
            "desc": ""
        },
        {
            "start": "18:02",
            "end": "18:28",
            "title": "兵器面面观-2026-131",
            "desc": ""
        },
        {
            "start": "18:28",
            "end": "19:00",
            "title": "国防故事-2026-87",
            "desc": ""
        },
        {
            "start": "19:00",
            "end": "19:33",
            "title": "新闻联播",
            "desc": ""
        },
        {
            "start": "19:33",
            "end": "20:03",
            "title": "军事报道",
            "desc": ""
        },
        {
            "start": "20:03",
            "end": "20:09",
            "title": "国防微视频-军歌嘹亮-人民海军向前进（2026）",
            "desc": ""
        },
        {
            "start": "20:09",
            "end": "20:39",
            "title": "防务新观察-2026-183",
            "desc": ""
        },
        {
            "start": "20:39",
            "end": "21:08",
            "title": "国防故事-2026-102",
            "desc": ""
        },
        {
            "start": "21:08",
            "end": "21:41",
            "title": "军事纪实-2026-131",
            "desc": ""
        },
        {
            "start": "21:41",
            "end": "22:17",
            "title": "砺剑-2026-27",
            "desc": ""
        },
        {
            "start": "22:17",
            "end": "23:08",
            "title": "五星剧场-我们的河山17/36",
            "desc": ""
        },
        {
            "start": "23:08",
            "end": "23:59",
            "title": "五星剧场-我们的河山18/36",
            "desc": ""
        }
    ]
}