{
    "channel_name": "东方卫视",
    "date": "2026-04-30",
    "epg_data": [
        {
            "start": "00:20",
            "end": "01:01",
            "title": "电视剧：繁华似锦(33)",
            "desc": ""
        },
        {
            "start": "01:01",
            "end": "01:42",
            "title": "电视剧：繁华似锦(34)",
            "desc": ""
        },
        {
            "start": "01:42",
            "end": "02:23",
            "title": "电视剧：繁华似锦(35)",
            "desc": ""
        },
        {
            "start": "02:23",
            "end": "03:05",
            "title": "电视剧：繁华似锦(36)",
            "desc": ""
        },
        {
            "start": "03:05",
            "end": "03:47",
            "title": "电视剧：繁华似锦(37)",
            "desc": ""
        },
        {
            "start": "03:47",
            "end": "04:28",
            "title": "电视剧：繁华似锦(38)",
            "desc": ""
        },
        {
            "start": "04:28",
            "end": "05:10",
            "title": "电视剧：菩提树下(1)",
            "desc": ""
        },
        {
            "start": "05:10",
            "end": "05:51",
            "title": "电视剧：菩提树下(2)",
            "desc": ""
        },
        {
            "start": "05:51",
            "end": "07:00",
            "title": "电视剧：菩提树下(3)",
            "desc": ""
        },
        {
            "start": "07:00",
            "end": "07:01",
            "title": "中华人民共和国国歌",
            "desc": ""
        },
        {
            "start": "07:01",
            "end": "08:59",
            "title": "看东方",
            "desc": ""
        },
        {
            "start": "08:59",
            "end": "09:01",
            "title": "天气预报",
            "desc": ""
        },
        {
            "start": "09:01",
            "end": "09:44",
            "title": "电视剧：都挺好(21)",
            "desc": ""
        },
        {
            "start": "09:44",
            "end": "10:28",
            "title": "电视剧：都挺好(22)",
            "desc": ""
        },
        {
            "start": "10:28",
            "end": "11:12",
            "title": "电视剧：都挺好(23)",
            "desc": ""
        },
        {
            "start": "11:12",
            "end": "12:00",
            "title": "电视剧：都挺好(24)",
            "desc": ""
        },
        {
            "start": "12:00",
            "end": "12:26",
            "title": "午间30分",
            "desc": ""
        },
        {
            "start": "12:26",
            "end": "12:30",
            "title": "天气预报",
            "desc": ""
        },
        {
            "start": "12:30",
            "end": "12:42",
            "title": "ShanghaiEye",
            "desc": ""
        },
        {
            "start": "12:42",
            "end": "13:24",
            "title": "电视剧：他为什么依然单身(4)",
            "desc": ""
        },
        {
            "start": "13:24",
            "end": "14:08",
            "title": "电视剧：他为什么依然单身(5)",
            "desc": ""
        },
        {
            "start": "14:08",
            "end": "14:52",
            "title": "电视剧：他为什么依然单身(6)",
            "desc": ""
        },
        {
            "start": "14:52",
            "end": "15:36",
            "title": "电视剧：他为什么依然单身(7)",
            "desc": ""
        },
        {
            "start": "15:36",
            "end": "16:19",
            "title": "电视剧：他为什么依然单身(8)",
            "desc": ""
        },
        {
            "start": "16:19",
            "end": "17:02",
            "title": "电视剧：他为什么依然单身(9)",
            "desc": ""
        },
        {
            "start": "17:02",
            "end": "17:28",
            "title": "东方新娱乐",
            "desc": ""
        },
        {
            "start": "17:28",
            "end": "18:00",
            "title": "名医话养生·快闪医院(2)",
            "desc": ""
        },
        {
            "start": "18:00",
            "end": "18:57",
            "title": "东方新闻",
            "desc": ""
        },
        {
            "start": "18:57",
            "end": "19:00",
            "title": "天气预报",
            "desc": ""
        },
        {
            "start": "19:00",
            "end": "19:32",
            "title": "新闻联播",
            "desc": ""
        },
        {
            "start": "19:32",
            "end": "20:14",
            "title": "电视剧：蜜语纪(31)",
            "desc": ""
        },
        {
            "start": "20:14",
            "end": "20:23",
            "title": "明日精彩看点",
            "desc": ""
        },
        {
            "start": "20:23",
            "end": "20:30",
            "title": "东方看大剧",
            "desc": ""
        },
        {
            "start": "20:30",
            "end": "21:30",
            "title": "爱购上海五五购物节全球大直播",
            "desc": ""
        },
        {
            "start": "21:30",
            "end": "22:30",
            "title": "爱购上海五五购物节全球大直播",
            "desc": ""
        },
        {
            "start": "22:30",
            "end": "23:33",
            "title": "爱购上海五五购物节全球大直播",
            "desc": ""
        },
        {
            "start": "23:33",
            "end": "23:59",
            "title": "太湖之恋(3)",
            "desc": ""
        }
    ]
}