{
    "channel_name": "广东卫视",
    "date": "2024-04-13",
    "epg_data": [
        {
            "start": "00:54",
            "end": "02:12",
            "title": "柳堡的故事",
            "desc": ""
        },
        {
            "start": "02:12",
            "end": "02:36",
            "title": "香港味道(7)",
            "desc": ""
        },
        {
            "start": "02:36",
            "end": "03:26",
            "title": "秘境神草4(3)",
            "desc": ""
        },
        {
            "start": "03:26",
            "end": "04:15",
            "title": "秘境神草4(4)",
            "desc": ""
        },
        {
            "start": "04:15",
            "end": "05:07",
            "title": "秘境神草4(5)",
            "desc": ""
        },
        {
            "start": "05:07",
            "end": "05:58",
            "title": "闯关东(24)",
            "desc": ""
        },
        {
            "start": "05:58",
            "end": "06:57",
            "title": "闯关东(25)",
            "desc": ""
        },
        {
            "start": "06:57",
            "end": "07:00",
            "title": "早间天气预报",
            "desc": ""
        },
        {
            "start": "07:00",
            "end": "07:01",
            "title": "中华人民共和国国歌",
            "desc": ""
        },
        {
            "start": "07:01",
            "end": "07:28",
            "title": "广东新闻联播",
            "desc": ""
        },
        {
            "start": "07:28",
            "end": "07:39",
            "title": "海底小纵队7(16)",
            "desc": ""
        },
        {
            "start": "07:39",
            "end": "07:50",
            "title": "海底小纵队7(17)",
            "desc": ""
        },
        {
            "start": "07:50",
            "end": "08:04",
            "title": "海底小纵队7(18)",
            "desc": ""
        },
        {
            "start": "08:04",
            "end": "08:54",
            "title": "上午剧场:猎鹰1949(25)",
            "desc": ""
        },
        {
            "start": "08:54",
            "end": "09:36",
            "title": "上午剧场:猎鹰1949(26)",
            "desc": ""
        },
        {
            "start": "09:36",
            "end": "10:27",
            "title": "上午剧场:猎鹰1949(27)",
            "desc": ""
        },
        {
            "start": "10:27",
            "end": "11:19",
            "title": "上午剧场:猎鹰1949(28)",
            "desc": ""
        },
        {
            "start": "11:19",
            "end": "12:13",
            "title": "上午剧场:猎鹰1949(29)",
            "desc": ""
        },
        {
            "start": "12:13",
            "end": "13:02",
            "title": "老广的味道6(5):辣在岭南",
            "desc": ""
        },
        {
            "start": "13:02",
            "end": "13:51",
            "title": "下午茶剧场:苍狼(12)",
            "desc": ""
        },
        {
            "start": "13:51",
            "end": "14:33",
            "title": "下午茶剧场:苍狼(13)",
            "desc": ""
        },
        {
            "start": "14:33",
            "end": "15:20",
            "title": "下午茶剧场:苍狼(14)",
            "desc": ""
        },
        {
            "start": "15:20",
            "end": "16:15",
            "title": "下午茶剧场:苍狼(15)",
            "desc": ""
        },
        {
            "start": "16:15",
            "end": "17:09",
            "title": "下午茶剧场:苍狼(16)",
            "desc": ""
        },
        {
            "start": "17:09",
            "end": "18:06",
            "title": "下午茶剧场:苍狼(17)",
            "desc": ""
        },
        {
            "start": "18:06",
            "end": "18:30",
            "title": "生活大数据(13)",
            "desc": ""
        },
        {
            "start": "18:30",
            "end": "18:56",
            "title": "广东新闻联播",
            "desc": ""
        },
        {
            "start": "18:56",
            "end": "19:00",
            "title": "广东天气预报",
            "desc": ""
        },
        {
            "start": "19:00",
            "end": "19:34",
            "title": "转播中央台新闻联播",
            "desc": ""
        },
        {
            "start": "19:34",
            "end": "20:31",
            "title": "活力剧场:江河日上(21)",
            "desc": ""
        },
        {
            "start": "20:31",
            "end": "21:18",
            "title": "活力剧场:江河日上(22)",
            "desc": ""
        },
        {
            "start": "21:18",
            "end": "22:15",
            "title": "平语近人-习近平喜欢的典故3",
            "desc": ""
        },
        {
            "start": "22:15",
            "end": "22:40",
            "title": "晚间新闻",
            "desc": ""
        },
        {
            "start": "22:40",
            "end": "23:20",
            "title": "扫黑风暴(1)",
            "desc": ""
        },
        {
            "start": "23:20",
            "end": "23:59",
            "title": "扫黑风暴(2)",
            "desc": ""
        },
        {
            "start": "23:59",
            "end": "00:00",
            "title": "红日",
            "desc": ""
        }
    ]
}