{
    "channel_name": "海南卫视",
    "date": "2024-04-13",
    "epg_data": [
        {
            "start": "00:10",
            "end": "00:15",
            "title": "点赞海南",
            "desc": ""
        },
        {
            "start": "00:15",
            "end": "02:30",
            "title": "凌晨剧场",
            "desc": ""
        },
        {
            "start": "02:30",
            "end": "02:35",
            "title": "点赞海南",
            "desc": ""
        },
        {
            "start": "02:35",
            "end": "03:00",
            "title": "潮起海之南",
            "desc": ""
        },
        {
            "start": "03:00",
            "end": "03:50",
            "title": "卫视高尔夫",
            "desc": ""
        },
        {
            "start": "03:50",
            "end": "04:20",
            "title": "视界",
            "desc": ""
        },
        {
            "start": "04:20",
            "end": "04:58",
            "title": "动漫剧场",
            "desc": ""
        },
        {
            "start": "04:58",
            "end": "06:25",
            "title": "凌晨剧场",
            "desc": ""
        },
        {
            "start": "06:25",
            "end": "07:00",
            "title": "潮起海之南",
            "desc": ""
        },
        {
            "start": "07:00",
            "end": "07:01",
            "title": "中华人民共和国国歌",
            "desc": ""
        },
        {
            "start": "07:01",
            "end": "07:33",
            "title": "海南新闻联播",
            "desc": ""
        },
        {
            "start": "07:33",
            "end": "07:58",
            "title": "潮起海之南",
            "desc": ""
        },
        {
            "start": "07:58",
            "end": "08:03",
            "title": "点赞海南",
            "desc": ""
        },
        {
            "start": "08:03",
            "end": "08:33",
            "title": "视界",
            "desc": ""
        },
        {
            "start": "08:33",
            "end": "09:01",
            "title": "阳光剧场:飞哥大英雄 40",
            "desc": ""
        },
        {
            "start": "09:01",
            "end": "09:29",
            "title": "阳光剧场:飞哥大英雄 41",
            "desc": ""
        },
        {
            "start": "09:29",
            "end": "09:57",
            "title": "阳光剧场:飞哥大英雄 42",
            "desc": ""
        },
        {
            "start": "09:57",
            "end": "10:35",
            "title": "阳光剧场:飞哥大英雄 43",
            "desc": ""
        },
        {
            "start": "10:35",
            "end": "11:23",
            "title": "阳光剧场:飞哥大英雄 44",
            "desc": ""
        },
        {
            "start": "11:23",
            "end": "12:11",
            "title": "阳光剧场:飞哥大英雄 45",
            "desc": ""
        },
        {
            "start": "12:11",
            "end": "13:09",
            "title": "下午剧场:飞哥大英雄 46",
            "desc": ""
        },
        {
            "start": "13:09",
            "end": "13:57",
            "title": "下午剧场:飞哥大英雄 47",
            "desc": ""
        },
        {
            "start": "13:57",
            "end": "14:45",
            "title": "下午剧场:飞哥大英雄 48",
            "desc": ""
        },
        {
            "start": "14:45",
            "end": "15:33",
            "title": "下午剧场:飞哥大英雄 49",
            "desc": ""
        },
        {
            "start": "15:33",
            "end": "16:21",
            "title": "下午剧场:飞哥大英雄 50",
            "desc": ""
        },
        {
            "start": "16:21",
            "end": "17:09",
            "title": "下午剧场:飞哥大英雄 51",
            "desc": ""
        },
        {
            "start": "17:09",
            "end": "18:07",
            "title": "下午剧场:飞哥大英雄 52",
            "desc": ""
        },
        {
            "start": "18:07",
            "end": "18:15",
            "title": "天气预报",
            "desc": ""
        },
        {
            "start": "18:15",
            "end": "18:30",
            "title": "点赞海南",
            "desc": ""
        },
        {
            "start": "18:30",
            "end": "19:00",
            "title": "海南新闻联播",
            "desc": ""
        },
        {
            "start": "19:00",
            "end": "19:30",
            "title": "转播中央台新闻联播",
            "desc": ""
        },
        {
            "start": "19:30",
            "end": "19:55",
            "title": "潮起海之南",
            "desc": ""
        },
        {
            "start": "19:55",
            "end": "20:00",
            "title": "点赞海南",
            "desc": ""
        },
        {
            "start": "20:00",
            "end": "20:29",
            "title": "视界",
            "desc": ""
        },
        {
            "start": "20:29",
            "end": "21:13",
            "title": "金椰剧场:去有风的地方(33)",
            "desc": ""
        },
        {
            "start": "21:13",
            "end": "22:30",
            "title": "金椰剧场:去有风的地方(34)",
            "desc": ""
        },
        {
            "start": "22:30",
            "end": "23:20",
            "title": "女人辣么美",
            "desc": ""
        },
        {
            "start": "23:20",
            "end": "23:30",
            "title": "点赞海南",
            "desc": ""
        },
        {
            "start": "23:30",
            "end": "00:00",
            "title": "卫视高尔夫",
            "desc": ""
        }
    ]
}