{
    "channel_name": "金鹰卡通",
    "date": "2026-06-16",
    "epg_data": [
        {
            "start": "00:00",
            "end": "07:00",
            "title": "熊出没之神奇宝物",
            "desc": ""
        },
        {
            "start": "07:00",
            "end": "07:02",
            "title": "麦咭嗨唱会",
            "desc": ""
        },
        {
            "start": "07:02",
            "end": "07:11",
            "title": "熊熊帮帮团3(12)",
            "desc": ""
        },
        {
            "start": "07:11",
            "end": "07:21",
            "title": "熊熊帮帮团3(13)",
            "desc": ""
        },
        {
            "start": "07:21",
            "end": "07:31",
            "title": "熊熊帮帮团3(14)",
            "desc": ""
        },
        {
            "start": "07:31",
            "end": "07:41",
            "title": "熊熊帮帮团3(15)",
            "desc": ""
        },
        {
            "start": "07:41",
            "end": "07:51",
            "title": "熊熊帮帮团3(16)",
            "desc": ""
        },
        {
            "start": "07:51",
            "end": "08:01",
            "title": "熊熊帮帮团3(17)",
            "desc": ""
        },
        {
            "start": "08:01",
            "end": "08:10",
            "title": "熊熊帮帮团3(18)",
            "desc": ""
        },
        {
            "start": "08:10",
            "end": "08:20",
            "title": "熊熊帮帮团3(19)",
            "desc": ""
        },
        {
            "start": "08:20",
            "end": "08:30",
            "title": "熊熊帮帮团3(20)",
            "desc": ""
        },
        {
            "start": "08:30",
            "end": "08:40",
            "title": "熊熊帮帮团3(21)",
            "desc": ""
        },
        {
            "start": "08:40",
            "end": "08:50",
            "title": "熊熊帮帮团3(22)",
            "desc": ""
        },
        {
            "start": "08:50",
            "end": "09:00",
            "title": "熊熊帮帮团3(23)",
            "desc": ""
        },
        {
            "start": "09:00",
            "end": "09:13",
            "title": "喜羊羊与灰太狼之疯狂超能营(36)",
            "desc": ""
        },
        {
            "start": "09:13",
            "end": "09:27",
            "title": "喜羊羊与灰太狼之疯狂超能营(37)",
            "desc": ""
        },
        {
            "start": "09:27",
            "end": "09:41",
            "title": "喜羊羊与灰太狼之疯狂超能营(38)",
            "desc": ""
        },
        {
            "start": "09:41",
            "end": "09:55",
            "title": "喜羊羊与灰太狼之疯狂超能营(39)",
            "desc": ""
        },
        {
            "start": "09:55",
            "end": "10:09",
            "title": "喜羊羊与灰太狼之疯狂超能营(40)",
            "desc": ""
        },
        {
            "start": "10:09",
            "end": "10:23",
            "title": "喜羊羊与灰太狼之疯狂超能营(41)",
            "desc": ""
        },
        {
            "start": "10:23",
            "end": "10:36",
            "title": "喜羊羊与灰太狼之疯狂超能营(42)",
            "desc": ""
        },
        {
            "start": "10:36",
            "end": "10:50",
            "title": "喜羊羊与灰太狼之疯狂超能营(43)",
            "desc": ""
        },
        {
            "start": "10:50",
            "end": "11:04",
            "title": "喜羊羊与灰太狼之疯狂超能营(44)",
            "desc": ""
        },
        {
            "start": "11:04",
            "end": "11:18",
            "title": "喜羊羊与灰太狼之疯狂超能营(45)",
            "desc": ""
        },
        {
            "start": "11:18",
            "end": "11:32",
            "title": "喜羊羊与灰太狼之疯狂超能营(46)",
            "desc": ""
        },
        {
            "start": "11:32",
            "end": "11:46",
            "title": "喜羊羊与灰太狼之疯狂超能营(47)",
            "desc": ""
        },
        {
            "start": "11:46",
            "end": "12:00",
            "title": "喜羊羊与灰太狼之疯狂超能营(48)",
            "desc": ""
        },
        {
            "start": "12:00",
            "end": "12:07",
            "title": "奶龙搞怪大作战2(45)",
            "desc": ""
        },
        {
            "start": "12:07",
            "end": "12:14",
            "title": "奶龙搞怪大作战2(46)",
            "desc": ""
        },
        {
            "start": "12:14",
            "end": "12:21",
            "title": "奶龙搞怪大作战2(47)",
            "desc": ""
        },
        {
            "start": "12:21",
            "end": "12:28",
            "title": "奶龙搞怪大作战2(48)",
            "desc": ""
        },
        {
            "start": "12:28",
            "end": "12:35",
            "title": "奶龙搞怪大作战2(49)",
            "desc": ""
        },
        {
            "start": "12:35",
            "end": "12:42",
            "title": "奶龙搞怪大作战2(50)",
            "desc": ""
        },
        {
            "start": "12:42",
            "end": "12:49",
            "title": "奶龙搞怪大作战2(51)",
            "desc": ""
        },
        {
            "start": "12:49",
            "end": "12:56",
            "title": "奶龙搞怪大作战2(52)",
            "desc": ""
        },
        {
            "start": "12:56",
            "end": "13:03",
            "title": "奶龙与小七之大战暴暴龙(1)",
            "desc": ""
        },
        {
            "start": "13:03",
            "end": "13:10",
            "title": "奶龙与小七之大战暴暴龙(2)",
            "desc": ""
        },
        {
            "start": "13:10",
            "end": "13:17",
            "title": "奶龙与小七之大战暴暴龙(3)",
            "desc": ""
        },
        {
            "start": "13:17",
            "end": "13:24",
            "title": "奶龙与小七之大战暴暴龙(4)",
            "desc": ""
        },
        {
            "start": "13:24",
            "end": "13:31",
            "title": "奶龙与小七之大战暴暴龙(5)",
            "desc": ""
        },
        {
            "start": "13:31",
            "end": "13:38",
            "title": "奶龙与小七之大战暴暴龙(6)",
            "desc": ""
        },
        {
            "start": "13:38",
            "end": "13:45",
            "title": "奶龙与小七之大战暴暴龙(7)",
            "desc": ""
        },
        {
            "start": "13:45",
            "end": "13:52",
            "title": "奶龙与小七之大战暴暴龙(8)",
            "desc": ""
        },
        {
            "start": "13:52",
            "end": "14:00",
            "title": "奶龙与小七之大战暴暴龙(9)",
            "desc": ""
        },
        {
            "start": "14:00",
            "end": "14:10",
            "title": "熊出没之小小世界2(10)",
            "desc": ""
        },
        {
            "start": "14:10",
            "end": "14:21",
            "title": "熊出没之小小世界2(11)",
            "desc": ""
        },
        {
            "start": "14:21",
            "end": "14:32",
            "title": "熊出没之小小世界2(12)",
            "desc": ""
        },
        {
            "start": "14:32",
            "end": "14:43",
            "title": "熊出没之小小世界2(13)",
            "desc": ""
        },
        {
            "start": "14:43",
            "end": "14:54",
            "title": "熊出没之小小世界2(14)",
            "desc": ""
        },
        {
            "start": "14:54",
            "end": "15:05",
            "title": "熊出没之小小世界2(15)",
            "desc": ""
        },
        {
            "start": "15:05",
            "end": "15:16",
            "title": "熊出没之小小世界2(16)",
            "desc": ""
        },
        {
            "start": "15:16",
            "end": "15:27",
            "title": "熊出没之小小世界2(17)",
            "desc": ""
        },
        {
            "start": "15:27",
            "end": "15:38",
            "title": "熊出没之小小世界2(18)",
            "desc": ""
        },
        {
            "start": "15:38",
            "end": "15:49",
            "title": "熊出没之小小世界2(19)",
            "desc": ""
        },
        {
            "start": "15:49",
            "end": "16:00",
            "title": "熊出没之小小世界2(20)",
            "desc": ""
        },
        {
            "start": "16:00",
            "end": "16:12",
            "title": "熊熊帮帮团5(6)",
            "desc": ""
        },
        {
            "start": "16:12",
            "end": "16:24",
            "title": "熊熊帮帮团5(7)",
            "desc": ""
        },
        {
            "start": "16:24",
            "end": "16:36",
            "title": "熊熊帮帮团5(8)",
            "desc": ""
        },
        {
            "start": "16:36",
            "end": "16:48",
            "title": "熊熊帮帮团5(9)",
            "desc": ""
        },
        {
            "start": "16:48",
            "end": "17:00",
            "title": "熊熊帮帮团5(10)",
            "desc": ""
        },
        {
            "start": "17:00",
            "end": "17:10",
            "title": "麦咭嗨唱会,麦咭小食光(34)等",
            "desc": ""
        },
        {
            "start": "17:10",
            "end": "17:26",
            "title": "奇妙萌可之闪耀流星(17)",
            "desc": ""
        },
        {
            "start": "17:26",
            "end": "17:43",
            "title": "奇妙萌可之闪耀流星(18)",
            "desc": ""
        },
        {
            "start": "17:43",
            "end": "18:00",
            "title": "奇妙萌可之闪耀流星(19)",
            "desc": ""
        },
        {
            "start": "18:00",
            "end": "18:13",
            "title": "喜羊羊与灰太狼之疯狂超能营(10)",
            "desc": ""
        },
        {
            "start": "18:13",
            "end": "18:26",
            "title": "喜羊羊与灰太狼之疯狂超能营(11)",
            "desc": ""
        },
        {
            "start": "18:26",
            "end": "18:40",
            "title": "喜羊羊与灰太狼之疯狂超能营(12)",
            "desc": ""
        },
        {
            "start": "18:40",
            "end": "18:53",
            "title": "喜羊羊与灰太狼之疯狂超能营(13)",
            "desc": ""
        },
        {
            "start": "18:53",
            "end": "19:06",
            "title": "喜羊羊与灰太狼之疯狂超能营(14)",
            "desc": ""
        },
        {
            "start": "19:06",
            "end": "19:20",
            "title": "喜羊羊与灰太狼之疯狂超能营(15)",
            "desc": ""
        },
        {
            "start": "19:20",
            "end": "19:33",
            "title": "喜羊羊与灰太狼之疯狂超能营(16)",
            "desc": ""
        },
        {
            "start": "19:33",
            "end": "19:46",
            "title": "喜羊羊与灰太狼之疯狂超能营(17)",
            "desc": ""
        },
        {
            "start": "19:46",
            "end": "20:00",
            "title": "喜羊羊与灰太狼之疯狂超能营(18)",
            "desc": ""
        },
        {
            "start": "20:00",
            "end": "20:12",
            "title": "量子战队之恐龙守护3(25)",
            "desc": ""
        },
        {
            "start": "20:12",
            "end": "20:22",
            "title": "熊出没之神奇宝物(11)",
            "desc": ""
        },
        {
            "start": "20:22",
            "end": "20:33",
            "title": "熊出没之神奇宝物(12)",
            "desc": ""
        },
        {
            "start": "20:33",
            "end": "20:44",
            "title": "熊出没之神奇宝物(13)",
            "desc": ""
        },
        {
            "start": "20:44",
            "end": "20:55",
            "title": "熊出没之神奇宝物(14)",
            "desc": ""
        },
        {
            "start": "20:55",
            "end": "21:06",
            "title": "熊出没之神奇宝物(15)",
            "desc": ""
        },
        {
            "start": "21:06",
            "end": "21:16",
            "title": "熊出没之神奇宝物(16)",
            "desc": ""
        },
        {
            "start": "21:16",
            "end": "21:27",
            "title": "熊出没之神奇宝物(17)",
            "desc": ""
        },
        {
            "start": "21:27",
            "end": "21:38",
            "title": "熊出没之神奇宝物(18)",
            "desc": ""
        },
        {
            "start": "21:38",
            "end": "21:49",
            "title": "熊出没之神奇宝物(19)",
            "desc": ""
        },
        {
            "start": "21:49",
            "end": "22:00",
            "title": "熊出没之神奇宝物(20)",
            "desc": ""
        },
        {
            "start": "22:00",
            "end": "22:10",
            "title": "猪猪侠之超星五灵侠7(12)",
            "desc": ""
        },
        {
            "start": "22:10",
            "end": "22:21",
            "title": "猪猪侠之超星五灵侠7(13)",
            "desc": ""
        },
        {
            "start": "22:21",
            "end": "22:32",
            "title": "猪猪侠之超星五灵侠7(14)",
            "desc": ""
        },
        {
            "start": "22:32",
            "end": "22:43",
            "title": "猪猪侠之超星五灵侠7(15)",
            "desc": ""
        },
        {
            "start": "22:43",
            "end": "22:54",
            "title": "猪猪侠之超星五灵侠7(16)",
            "desc": ""
        },
        {
            "start": "22:54",
            "end": "23:05",
            "title": "猪猪侠之超星五灵侠7(17)",
            "desc": ""
        },
        {
            "start": "23:05",
            "end": "23:16",
            "title": "猪猪侠之超星五灵侠7(18)",
            "desc": ""
        },
        {
            "start": "23:16",
            "end": "23:27",
            "title": "猪猪侠之超星五灵侠7(19)",
            "desc": ""
        },
        {
            "start": "23:27",
            "end": "23:38",
            "title": "猪猪侠之超星五灵侠7(20)",
            "desc": ""
        },
        {
            "start": "23:38",
            "end": "23:49",
            "title": "猪猪侠之超星五灵侠7(21)",
            "desc": ""
        },
        {
            "start": "23:49",
            "end": "00:00",
            "title": "猪猪侠之超星五灵侠7(22)",
            "desc": ""
        }
    ]
}