{
    "channel_name": "CCTV5+体育赛事",
    "date": "2026-04-29",
    "epg_data": [
        {
            "start": "00:36",
            "end": "01:06",
            "title": "实况录像-精品赛事记录-2026年射箭世界杯墨西哥站 中国队金牌1",
            "desc": ""
        },
        {
            "start": "01:06",
            "end": "02:36",
            "title": "实况录像-2025/2026赛季中国男子篮球职业联赛 第33轮 辽宁本钢—新疆伊力特",
            "desc": ""
        },
        {
            "start": "02:36",
            "end": "04:00",
            "title": "国际足球赛场-25-26赛季英超联赛第10轮 诺丁汉森林—曼联",
            "desc": ""
        },
        {
            "start": "04:00",
            "end": "06:00",
            "title": "实况录像-2025/2026赛季斯诺克西安大奖赛 1",
            "desc": ""
        },
        {
            "start": "06:00",
            "end": "07:30",
            "title": "实况录像-2025年世界田联钻石联赛  罗马站",
            "desc": ""
        },
        {
            "start": "07:30",
            "end": "08:30",
            "title": "2026年蹦床世界杯-阿尔克马尔站1",
            "desc": ""
        },
        {
            "start": "08:30",
            "end": "09:50",
            "title": "2025/2026赛季中国排球超级联赛-女排决赛第二场",
            "desc": ""
        },
        {
            "start": "09:50",
            "end": "10:00",
            "title": "实况录像-荣耀十分-2026年艺术体操世界杯索菲亚站 中国队获集体5球单项金牌",
            "desc": ""
        },
        {
            "start": "10:00",
            "end": "11:06",
            "title": "2026年第六届亚沙会-沙滩排球女子决赛",
            "desc": ""
        },
        {
            "start": "11:06",
            "end": "12:07",
            "title": "实况录像-2026年世界泳联花样游泳世界杯 法国站  3",
            "desc": ""
        },
        {
            "start": "12:07",
            "end": "12:22",
            "title": "实况录像-荣耀十分-2026年蹦床世界杯 阿尔克马尔站 王梓赛获金牌",
            "desc": ""
        },
        {
            "start": "12:22",
            "end": "13:23",
            "title": "实况录像-2026年全国举重锦标赛 男子比赛1",
            "desc": ""
        },
        {
            "start": "13:23",
            "end": "14:55",
            "title": "2025/2026德国足球甲级联赛-第31轮（汉堡—霍芬海姆）（4K）",
            "desc": ""
        },
        {
            "start": "14:55",
            "end": "15:58",
            "title": "实况录像-2026年国际乒联单打世界杯 1",
            "desc": ""
        },
        {
            "start": "15:58",
            "end": "16:30",
            "title": "实况录像-2026年体操世界杯 科特布斯站 25分钟版",
            "desc": ""
        },
        {
            "start": "16:30",
            "end": "18:00",
            "title": "实况录像-2025/2026赛季中国男子篮球职业联赛 季后赛12进8 第一场1",
            "desc": ""
        },
        {
            "start": "18:00",
            "end": "20:00",
            "title": "2026年第六届亚沙会-三人篮球铜牌赛、决赛",
            "desc": ""
        },
        {
            "start": "20:00",
            "end": "22:00",
            "title": "国际冰球联合会男子冰球世锦赛-甲级B组（中国队—韩国队）",
            "desc": ""
        },
        {
            "start": "22:00",
            "end": "23:59",
            "title": "2026年ATP1000男子网球大师赛-马德里站 1/4决赛",
            "desc": ""
        }
    ]
}