{
    "channel_name": "探索频道",
    "date": "2024-05-10",
    "epg_data": [
        {
            "start": "00:00",
            "end": "01:00",
            "title": "沉默片場:童星的黑暗面:最黑暗的秘密",
            "desc": ""
        },
        {
            "start": "01:00",
            "end": "02:00",
            "title": "翻新中古車:美夢成真:哈連的日產",
            "desc": ""
        },
        {
            "start": "02:00",
            "end": "03:00",
            "title": "跟著貝爾闖荒野:拉吉尼",
            "desc": ""
        },
        {
            "start": "03:00",
            "end": "04:00",
            "title": "單挑荒野:波札那",
            "desc": ""
        },
        {
            "start": "04:00",
            "end": "05:00",
            "title": "求生1加1巴西篇:維塔斯",
            "desc": ""
        },
        {
            "start": "05:00",
            "end": "06:00",
            "title": "私酒大鬥法第11季:甜蜜家園",
            "desc": ""
        },
        {
            "start": "06:00",
            "end": "07:00",
            "title": "金礦的賭注第14季:唯一指望",
            "desc": ""
        },
        {
            "start": "07:00",
            "end": "08:00",
            "title": "舊貨獵人第16季:第10集",
            "desc": ""
        },
        {
            "start": "08:00",
            "end": "09:00",
            "title": "泥地卡車賽:廢鐵成堆",
            "desc": ""
        },
        {
            "start": "09:00",
            "end": "10:00",
            "title": "翻新中古車:美夢成真:亞當的TVR",
            "desc": ""
        },
        {
            "start": "10:00",
            "end": "11:00",
            "title": "拿命來求職:硬著頭皮",
            "desc": ""
        },
        {
            "start": "11:00",
            "end": "12:00",
            "title": "舊貨獵人修復篇第3季:漂亮粉紅",
            "desc": ""
        },
        {
            "start": "12:00",
            "end": "13:00",
            "title": "舊貨獵人第16季:第10集",
            "desc": ""
        },
        {
            "start": "13:00",
            "end": "14:00",
            "title": "金礦的賭注第14季:唯一指望",
            "desc": ""
        },
        {
            "start": "14:00",
            "end": "15:00",
            "title": "翻新中古車:美夢成真:亞當的TVR",
            "desc": ""
        },
        {
            "start": "15:00",
            "end": "16:00",
            "title": "拿命來求職:硬著頭皮",
            "desc": ""
        },
        {
            "start": "16:00",
            "end": "17:00",
            "title": "金礦的賭注急流篇第5季:爆發臨界點",
            "desc": ""
        },
        {
            "start": "17:00",
            "end": "18:00",
            "title": "小勞勃道尼打造夢幻車:薩諾斯重鎚",
            "desc": ""
        },
        {
            "start": "18:00",
            "end": "19:00",
            "title": "金礦的賭注第14季:唯一指望",
            "desc": ""
        },
        {
            "start": "19:00",
            "end": "20:00",
            "title": "舊貨獵人第16季:第11集",
            "desc": ""
        },
        {
            "start": "20:00",
            "end": "21:00",
            "title": "野地造屋第6季:山區三角屋",
            "desc": ""
        },
        {
            "start": "21:00",
            "end": "22:00",
            "title": "蛋白石獵人越野去:第1集",
            "desc": ""
        },
        {
            "start": "22:00",
            "end": "23:00",
            "title": "沉默片場:童星的黑暗面:靠近核心",
            "desc": ""
        },
        {
            "start": "23:00",
            "end": "00:00",
            "title": "盲蛙牧場藏寶之謎第3季:阿茲特克明證",
            "desc": ""
        }
    ]
}