{
    "channel_name": "贵州卫视",
    "date": "2024-04-11",
    "epg_data": [
        {
            "start": "00:01",
            "end": "00:26",
            "title": "贵州新闻联播",
            "desc": ""
        },
        {
            "start": "00:26",
            "end": "00:28",
            "title": "多彩贵州旅游天气导航",
            "desc": ""
        },
        {
            "start": "00:28",
            "end": "01:13",
            "title": "凭栏一片风云起37",
            "desc": ""
        },
        {
            "start": "01:13",
            "end": "01:55",
            "title": "凭栏一片风云起38",
            "desc": ""
        },
        {
            "start": "01:55",
            "end": "02:42",
            "title": "凭栏一片风云起39",
            "desc": ""
        },
        {
            "start": "02:42",
            "end": "03:09",
            "title": "詹姆士的厨房",
            "desc": ""
        },
        {
            "start": "03:09",
            "end": "03:44",
            "title": "詹姆士的厨房",
            "desc": ""
        },
        {
            "start": "03:44",
            "end": "04:39",
            "title": "纪录片:中国第三季3",
            "desc": ""
        },
        {
            "start": "04:39",
            "end": "05:23",
            "title": "凭栏一片风云起40",
            "desc": ""
        },
        {
            "start": "05:23",
            "end": "06:03",
            "title": "甜蜜1",
            "desc": ""
        },
        {
            "start": "06:03",
            "end": "06:17",
            "title": "纪录片:早餐中国第四季",
            "desc": ""
        },
        {
            "start": "06:17",
            "end": "06:34",
            "title": "纪录片:早餐中国第三季",
            "desc": ""
        },
        {
            "start": "06:34",
            "end": "07:00",
            "title": "贵州新闻联播",
            "desc": ""
        },
        {
            "start": "07:00",
            "end": "07:01",
            "title": "中华人民共和国国歌",
            "desc": ""
        },
        {
            "start": "07:01",
            "end": "08:02",
            "title": "等着我",
            "desc": ""
        },
        {
            "start": "08:02",
            "end": "08:29",
            "title": "动画片:开心超人联盟之奇幻谜瑞岛",
            "desc": ""
        },
        {
            "start": "08:29",
            "end": "09:46",
            "title": "上午剧场:雪鹰18",
            "desc": ""
        },
        {
            "start": "09:46",
            "end": "11:00",
            "title": "上午剧场:雪鹰19",
            "desc": ""
        },
        {
            "start": "11:00",
            "end": "11:58",
            "title": "上午剧场:雪鹰20",
            "desc": ""
        },
        {
            "start": "11:58",
            "end": "12:52",
            "title": "上午剧场:雪鹰21",
            "desc": ""
        },
        {
            "start": "12:52",
            "end": "13:47",
            "title": "上午剧场:雪鹰22",
            "desc": ""
        },
        {
            "start": "13:47",
            "end": "13:53",
            "title": "气象快讯",
            "desc": ""
        },
        {
            "start": "13:53",
            "end": "14:47",
            "title": "下午剧场:雪鹰23",
            "desc": ""
        },
        {
            "start": "14:47",
            "end": "15:40",
            "title": "下午剧场:雪鹰24",
            "desc": ""
        },
        {
            "start": "15:40",
            "end": "16:34",
            "title": "下午剧场:雪鹰25",
            "desc": ""
        },
        {
            "start": "16:34",
            "end": "17:47",
            "title": "下午剧场:雪鹰26",
            "desc": ""
        },
        {
            "start": "17:47",
            "end": "18:00",
            "title": "历史上的今天",
            "desc": ""
        },
        {
            "start": "18:00",
            "end": "18:30",
            "title": "动静新闻",
            "desc": ""
        },
        {
            "start": "18:30",
            "end": "18:56",
            "title": "贵州新闻联播",
            "desc": ""
        },
        {
            "start": "18:56",
            "end": "19:00",
            "title": "天气预报",
            "desc": ""
        },
        {
            "start": "19:00",
            "end": "19:35",
            "title": "转播中央台新闻联播",
            "desc": ""
        },
        {
            "start": "19:35",
            "end": "20:19",
            "title": "南洋女儿情11",
            "desc": ""
        },
        {
            "start": "20:19",
            "end": "20:28",
            "title": "广告",
            "desc": ""
        },
        {
            "start": "20:28",
            "end": "21:10",
            "title": "南洋女儿情12",
            "desc": ""
        },
        {
            "start": "21:10",
            "end": "21:20",
            "title": "广告",
            "desc": ""
        },
        {
            "start": "21:20",
            "end": "22:00",
            "title": "叙非遗苗艺",
            "desc": ""
        },
        {
            "start": "22:00",
            "end": "23:01",
            "title": "三大队20",
            "desc": ""
        },
        {
            "start": "23:01",
            "end": "23:04",
            "title": "欢乐喜剧人精选",
            "desc": ""
        },
        {
            "start": "23:04",
            "end": "23:22",
            "title": "小品",
            "desc": ""
        },
        {
            "start": "23:22",
            "end": "00:00",
            "title": "健康密码",
            "desc": ""
        }
    ]
}